odoo/addons/survey_skip_start/README.rst
odoo/addons/survey_skip_start/__init__.py
odoo/addons/survey_skip_start/__manifest__.py
odoo/addons/survey_skip_start/controllers/__init__.py
odoo/addons/survey_skip_start/controllers/main.py
odoo/addons/survey_skip_start/i18n/es.po
odoo/addons/survey_skip_start/i18n/it.po
odoo/addons/survey_skip_start/i18n/survey_skip_start.pot
odoo/addons/survey_skip_start/models/__init__.py
odoo/addons/survey_skip_start/models/survey_survey.py
odoo/addons/survey_skip_start/readme/CONFIGURE.md
odoo/addons/survey_skip_start/readme/CONTEXT.md
odoo/addons/survey_skip_start/readme/CONTRIBUTORS.md
odoo/addons/survey_skip_start/readme/DESCRIPTION.md
odoo/addons/survey_skip_start/readme/ROADMAP.md
odoo/addons/survey_skip_start/readme/USAGE.md
odoo/addons/survey_skip_start/static/description/icon.png
odoo/addons/survey_skip_start/static/description/index.html
odoo/addons/survey_skip_start/static/tests/survey_skip_start_tour.esm.js
odoo/addons/survey_skip_start/tests/__init__.py
odoo/addons/survey_skip_start/tests/test_survey_skip_start.py
odoo/addons/survey_skip_start/views/survey_survey_views.xml
odoo_addon_survey_skip_start-17.0.1.0.2.dist-info/METADATA
odoo_addon_survey_skip_start-17.0.1.0.2.dist-info/WHEEL
odoo_addon_survey_skip_start-17.0.1.0.2.dist-info/top_level.txt
odoo_addon_survey_skip_start-17.0.1.0.2.dist-info/RECORD
